veriteem/AccessControl.py
veriteem/AutoRun.py
veriteem/Config.py
veriteem/Configure.py
veriteem/InitGeth.py
veriteem/README.md
veriteem/StartMiner.py
veriteem/StartVeriteem.py
veriteem/Veriteem.py
veriteem/VeriteemConfig.py
veriteem/VeriteemInstall.py
veriteem/__init__.py
veriteem/assets/Config.json
veriteem/assets/LoadZigBee.js
veriteem/assets/errors.go
veriteem/assets/evm.go
veriteem/assets/genesis.json
veriteem/bin/installgo.sh
veriteem/scripts/AccessRights.js
veriteem/scripts/AccessRights.sol
veriteem/scripts/AccessRightsAddress.js
veriteem/scripts/AddAccessRights.js
veriteem/scripts/LoadAccessRights.js
veriteem/scripts/LoadComplianceLedger.js
veriteem-0.3.4.data/scripts/Veriteem.py
veriteem-0.3.4.data/scripts/VeriteemConfig.py
veriteem-0.3.4.dist-info/DESCRIPTION.rst
veriteem-0.3.4.dist-info/METADATA
veriteem-0.3.4.dist-info/RECORD
veriteem-0.3.4.dist-info/WHEEL
veriteem-0.3.4.dist-info/metadata.json
veriteem-0.3.4.dist-info/top_level.txt
