Metadata-Version: 2.0
Name: veriteem
Version: 0.3.4
Summary: Veriteem Blockchain DLT
Home-page: https://github.com/VerimatrixGen1/Veriteem
Author: Brad Ree
Author-email: bree@verimatrix.com
License: GPL
Project-URL: Source Code, https://github.com/VerimatrixGen1/Veriteem
Project-URL: Documentation, https://github.com/VerimatrixGen1/Veriteem/wiki
Project-URL: Bug Tracker, https://bugs.example.com/HelloWorld/
Keywords: Verimatrix Blockchain Compliance Ledger
Platform: UNKNOWN
